ilightsln/__init__.py
ilightsln/ilightsln.py
ilightsln-0.0.1.dist-info/LICENSE
ilightsln-0.0.1.dist-info/METADATA
ilightsln-0.0.1.dist-info/WHEEL
ilightsln-0.0.1.dist-info/top_level.txt
ilightsln-0.0.1.dist-info/RECORD
