Metadata-Version: 2.1
Name: ilightsln
Version: 0.0.1
Summary: Connect to a ILightSln zigbee gateway via network to control the lights
Home-page: https://github.com/DavidLP/ilightsln
Author: David-Leon Pohl
Author-email: David-Leon.Pohl@rub.de
Maintainer: David-Leon Pohl
Maintainer-email: David-Leon.Pohl@rub.de
License: MIT License
Keywords: zigbee,light
Platform: any
